setup.py
heptet_app_sqlalchemy/__init__.py
heptet_app_sqlalchemy.egg-info/PKG-INFO
heptet_app_sqlalchemy.egg-info/SOURCES.txt
heptet_app_sqlalchemy.egg-info/dependency_links.txt
heptet_app_sqlalchemy.egg-info/entry_points.txt
heptet_app_sqlalchemy.egg-info/not-zip-safe
heptet_app_sqlalchemy.egg-info/requires.txt
heptet_app_sqlalchemy.egg-info/top_level.txt