Metadata-Version: 2.1
Name: heptet-app-sqlalchemy
Version: 0.45.0
Summary: Heptet App SQLAlchemy component
Home-page: UNKNOWN
Author: Kay McCormick
Author-email: kay@kaymccormick.com
License: UNKNOWN
Keywords: web pyramid pylons
Platform: UNKNOWN
Classifier: Programming Language :: Python
Classifier: Framework :: Pyramid
Classifier: Topic :: Internet :: WWW/HTTP
Classifier: Topic :: Internet :: WWW/HTTP :: WSGI :: Application
Provides-Extra: testing
